Metadata-Version: 2.1
Name: ygame-engine
Version: 0.1.4
Summary: Engine for the ygame bot challenge in UFDS
Home-page: https://youtu.be/dQw4w9WgXcQ
Author: Oviyan Gandhi
Author-email: oviyangandhi@gmail.com
License: UNKNOWN
Platform: UNKNOWN
Classifier: Programming Language :: Python :: 3
Classifier: License :: OSI Approved :: MIT License
Classifier: Operating System :: OS Independent
